Metadata-Version: 2.1
Name: twitter-automate
Version: 1.0.3
Summary: This library allow to do automatisation actions like, share and comment on Twitter
Home-page: https://gitlab.kaisens.fr/amouhite02/automatisation-rs
Author: ADEBO
Author-email: madebo@kaisensdata.fr
License: MIT
Keywords: automate,twitter-automate,twitter,automatisation
Platform: UNKNOWN
Classifier: Programming Language :: Python :: 3.8
Classifier: Operating System :: OS Independent
Requires-Python: >=3.5
